nat/meta/pypi.md
nat/plugins/vanna/__init__.py
nat/plugins/vanna/db_utils.py
nat/plugins/vanna/execute_db_query.py
nat/plugins/vanna/register.py
nat/plugins/vanna/text2sql.py
nat/plugins/vanna/training_db_schema.py
nat/plugins/vanna/vanna_utils.py
nvidia_nat_vanna-1.5.0a20260130.dist-info/METADATA
nvidia_nat_vanna-1.5.0a20260130.dist-info/WHEEL
nvidia_nat_vanna-1.5.0a20260130.dist-info/entry_points.txt
nvidia_nat_vanna-1.5.0a20260130.dist-info/top_level.txt
nvidia_nat_vanna-1.5.0a20260130.dist-info/RECORD
