Metadata-Version: 2.4
Name: nvidia-nat-vanna
Version: 1.5.0a20260130
Summary: Vanna-based Text-to-SQL integration for NeMo Agent Toolkit with Databricks support
Keywords: ai,agents,text2sql,vanna,sql,database
Classifier: Programming Language :: Python
Classifier: Programming Language :: Python :: 3.11
Classifier: Programming Language :: Python :: 3.12
Classifier: Programming Language :: Python :: 3.13
Requires-Python: <3.14,>=3.11
Requires-Dist: nvidia-nat[langchain]==v1.5.0a20260130
Requires-Dist: databricks-sql-connector<5.0.0,>=4.1.4
Requires-Dist: databricks-sqlalchemy<3.0.0,>=2.0.8
Requires-Dist: pandas~=2.0
Requires-Dist: pymilvus[model]~=2.6
Requires-Dist: sqlglot~=26.33
Requires-Dist: vanna[chromadb]<3.0.0,>=2.0.1
